nidalee/__init__.py
nidalee/bayes_connection.py
nidalee/match.py
nidalee/utils.py
nidalee/assets/__init__.py
nidalee/assets/blueCamp.png
nidalee/assets/dragon.png
nidalee/assets/gromp.png
nidalee/assets/krug.png
nidalee/assets/raptor.png
nidalee/assets/redCamp.png
nidalee/assets/scuttleCrab.png
nidalee/assets/summoners_rift.png
nidalee/assets/wolf.png
nidalee-0.1.28.dist-info/METADATA
nidalee-0.1.28.dist-info/WHEEL
nidalee-0.1.28.dist-info/top_level.txt
nidalee-0.1.28.dist-info/RECORD
